[
    {
        "url": "/home/list",
        "method": "post",
        "desc": "首页列表",
        "name": "/home/list"
    },
    {
        "url": "/api/announcement/list",
        "method": "get",
        "desc": "公告",
        "name": "/api/announcement/list"
    },
    {
        "url": "/api/rotationChart/selectRotationChartList",
        "method": "get",
        "desc": "首页 banner",
        "name": "/api/rotationChart/selectRotationChartList"
    },
    {
        "url": "/api/homePosition/selectNftHomePositionList",
        "method": "get",
        "desc": "金刚区",
        "name": "/api/homePosition/selectNftHomePositionList"
    },
    {
        "url": "/api/announcement/type/selectAnnouncementTypeList",
        "method": "get",
        "desc": "公告 Tab",
        "name": "/api/announcement/type/selectAnnouncementTypeList"
    },
    {
        "url": "/nft/market/getPlateList",
        "method": "get",
        "desc": "寄售市场二级分类",
        "name": "/nft/market/getPlateList"
    },
    {
        "url": "/nft/market/getConsignmentProductList",
        "method": "post",
        "desc": "寄售市场二级藏品列表",
        "name": "/nft/market/getConsignmentProductList"
    },
    {
        "url": "/wx/user",
        "method": "get",
        "desc": "个人信息",
        "name": "/wx/user"
    },
    {
        "url": "/nft/user/product/getProductList",
        "method": "get",
        "desc": "数字藏品列表",
        "name": "/nft/user/product/getProductList"
    },
    {
        "url": "/api/app/login/phone",
        "method": "post",
        "desc": "登陆",
        "name": "/api/app/login/phone"
    },
    {
        "url": "/nft/market/getProductMintDetails",
        "method": "get",
        "desc": "藏品详情",
        "name": "/nft/market/getProductMintDetails"
    },
    {
        "url": "/nft/market/getConsignmentList",
        "method": "get",
        "desc": "寄售市场列表",
        "name": "/nft/market/getConsignmentList"
    },
    {
        "url": "/nft/order/createBuyOrder",
        "method": "post",
        "desc": "创建订单",
        "name": "/nft/order/createBuyOrder"
    },
    {
        "url": "/nft/order/getOrderList",
        "method": "get",
        "desc": "查询订单",
        "name": "/nft/order/getOrderList"
    }
]